chemdescriptor/__init__.py
chemdescriptor/command_line.py
chemdescriptor/defaults/__init__.py
chemdescriptor/defaults/cxcalc.py
chemdescriptor/defaults/rdkit.py
chemdescriptor/generator/__init__.py
chemdescriptor/generator/base.py
chemdescriptor/generator/chemaxon.py
chemdescriptor/generator/openbabel.py
chemdescriptor/generator/rdkit.py
chemdescriptor-0.2.4.dist-info/LICENSE
chemdescriptor-0.2.4.dist-info/METADATA
chemdescriptor-0.2.4.dist-info/WHEEL
chemdescriptor-0.2.4.dist-info/entry_points.txt
chemdescriptor-0.2.4.dist-info/top_level.txt
chemdescriptor-0.2.4.dist-info/RECORD
