Metadata-Version: 2.1
Name: chemdescriptor
Version: 0.2.4
Summary: A standalone module to help generate molecular descriptors from various cheminformatics software
Home-page: https://github.com/darkreactions/chemdescriptor
Author: DRP Project
Author-email: darkreactionproject@haverford.edu
License: UNKNOWN
Platform: UNKNOWN
Classifier: Programming Language :: Python :: 3
Classifier: License :: OSI Approved :: MIT License
Classifier: Operating System :: OS Independent
Requires-Dist: pandas
